disbatch/__init__.py
disbatch/__main__.py
disbatch/_version.py
disbatch/dbMon.py
disbatch/dbUtil.template.sh
disbatch/disBatch.py
disbatch/kvsstcp/.gitignore
disbatch/kvsstcp/Readme.md
disbatch/kvsstcp/__init__.py
disbatch/kvsstcp/kvsclient.py
disbatch/kvsstcp/kvscommon.py
disbatch/kvsstcp/kvsstcp.py
disbatch-3.0.dist-info/METADATA
disbatch-3.0.dist-info/WHEEL
disbatch-3.0.dist-info/entry_points.txt
disbatch-3.0.dist-info/licenses/LICENSE
disbatch-3.0.dist-info/RECORD
