Metadata-Version: 2.3
Name: disbatch
Version: 3.0
Summary: Dynamically distribute a list of tasks over a pool of compute resources
Author: Nick Carriero
Author-email: Lehman Garrison <lgarrison@flatironinstitute.org>
License: 
Requires-Python: >=3.9
